mailserveradmin/__init__.py
mailserveradmin/auth.py
mailserveradmin/forms.py
mailserveradmin/urls.py
mailserveradmin/config/__init__.py
mailserveradmin/config/asgi.py
mailserveradmin/config/django.py
mailserveradmin/config/settings.py
mailserveradmin/config/urls.py
mailserveradmin/config/wsgi.py
mailserveradmin/migrations/0001_initial.py
mailserveradmin/migrations/__init__.py
mailserveradmin/models/__init__.py
mailserveradmin/models/alias.py
mailserveradmin/models/common.py
mailserveradmin/models/domain.py
mailserveradmin/models/user.py
mailserveradmin/static/favicon.ico
mailserveradmin/static/mailserveradmin/css/app.css
mailserveradmin/static/mailserveradmin/js/app.js
mailserveradmin/templates/mailserveradmin/base.html
mailserveradmin/templates/mailserveradmin/base_create.html
mailserveradmin/templates/mailserveradmin/base_crud.html
mailserveradmin/templates/mailserveradmin/base_dashboard.html
mailserveradmin/templates/mailserveradmin/base_delete.html
mailserveradmin/templates/mailserveradmin/base_detail.html
mailserveradmin/templates/mailserveradmin/base_edit.html
mailserveradmin/templates/mailserveradmin/base_list.html
mailserveradmin/templates/mailserveradmin/column_data.html
mailserveradmin/templates/mailserveradmin/column_header.html
mailserveradmin/templates/mailserveradmin/field_detail.html
mailserveradmin/templates/mailserveradmin/footer.html
mailserveradmin/templates/mailserveradmin/login.html
mailserveradmin/templates/mailserveradmin/mailalias_confirm_delete.html
mailserveradmin/templates/mailserveradmin/mailalias_create.html
mailserveradmin/templates/mailserveradmin/mailalias_detail.html
mailserveradmin/templates/mailserveradmin/mailalias_edit.html
mailserveradmin/templates/mailserveradmin/mailalias_list.html
mailserveradmin/templates/mailserveradmin/maildomain_confirm_delete.html
mailserveradmin/templates/mailserveradmin/maildomain_create.html
mailserveradmin/templates/mailserveradmin/maildomain_detail.html
mailserver_admin-0.9.0.dist-info/LICENSE
mailserver_admin-0.9.0.dist-info/METADATA
mailserver_admin-0.9.0.dist-info/WHEEL
mailserver_admin-0.9.0.dist-info/entry_points.txt
mailserver_admin-0.9.0.dist-info/top_level.txt
mailserver_admin-0.9.0.dist-info/RECORD
