Metadata-Version: 2.1
Name: mailserver-admin
Version: 0.9.0
Summary: Webapp to manage mail server domains, users and aliases.
Home-page: https://github.com/jrd/mailserver-admin
Author: Cyrille Pontvieux
Author-email: cyrille@enialis.net
License: MIT
Project-URL: Source, https://github.com/jrd/mailserver-admin
Project-URL: Docker, https://hub.docker.com/repository/docker/jrdasm/mailserver-admin
Keywords: email mail domain admin
Platform: UNKNOWN
Classifier: Development Status :: 4 - Beta
Classifier: Environment :: Web Environment
Classifier: Framework :: Django :: 3.1
Classifier: Intended Audience :: System Administrators
Classifier: License :: OSI Approved :: MIT License
Classifier: Natural Language :: English
Classifier: Operating System :: OS Independent
Classifier: Programming Language :: Python :: 3
Classifier: Programming Language :: Python :: 3 :: Only
Classifier: Programming Language :: Python :: 3.9
Classifier: Programming Language :: Python :: 3.10
Classifier: Topic :: Communications :: Email
Classifier: Topic :: Internet :: WWW/HTTP
Classifier: Topic :: Internet :: WWW/HTTP :: WSGI :: Application
Classifier: Topic :: System :: Systems Administration
Requires-Python: >=3.9
Requires-Dist: django (~=3.1)
Requires-Dist: fontawesome-free (~=5.14)
Requires-Dist: pycryptodome (~=3.0)
Requires-Dist: dnspython (~=1.0)
Provides-Extra: mysql
Requires-Dist: mysqlclient (~=2.0) ; extra == 'mysql'
Provides-Extra: postgresql
Requires-Dist: psycopg2-binary (~=2.8) ; extra == 'postgresql'
